.gitignore
LICENSE
MANIFEST.in
README.md
README.rst
reinstall
setup.py
GOldwasher/__init__.py
GOldwasher/enricher.py
GOldwasher/hoarder.py
GOldwasher/misc.py
GOldwasher/oboe.py
GOldwasher/organisms.json
GOldwasher/setup.py
GOldwasher.egg-info/PKG-INFO
GOldwasher.egg-info/SOURCES.txt
GOldwasher.egg-info/dependency_links.txt
GOldwasher.egg-info/not-zip-safe
GOldwasher.egg-info/requires.txt
GOldwasher.egg-info/top_level.txt
GOldwasher/libraries/__init__.py
GOldwasher/libraries/ontology.py
GOldwasher/libraries/support/custom.css
GOldwasher/libraries/support/sorttable.js
GOldwasher/libraries/support/jquery/AUTHORS.txt
GOldwasher/libraries/support/jquery/LICENSE.txt
GOldwasher/libraries/support/jquery/jquery-1.10.2.js
GOldwasher/libraries/support/jquery/jquery-ui.css
GOldwasher/libraries/support/jquery/jquery-ui.js
GOldwasher/libraries/support/jquery/images/ui-icons_444444_256x240.png
GOldwasher/libraries/support/jquery/images/ui-icons_555555_256x240.png
GOldwasher/libraries/support/jquery/images/ui-icons_777620_256x240.png
GOldwasher/libraries/support/jquery/images/ui-icons_777777_256x240.png
GOldwasher/libraries/support/jquery/images/ui-icons_cc0000_256x240.png
GOldwasher/libraries/support/jquery/images/ui-icons_ffffff_256x240.png
GOldwasher/libraries/support/svg-pan-zoom/LICENSE
GOldwasher/libraries/support/svg-pan-zoom/browserify.js
GOldwasher/libraries/support/svg-pan-zoom/control-icons.js
GOldwasher/libraries/support/svg-pan-zoom/shadow-viewport.js
GOldwasher/libraries/support/svg-pan-zoom/stand-alone.js
GOldwasher/libraries/support/svg-pan-zoom/svg-pan-zoom.js
GOldwasher/libraries/support/svg-pan-zoom/svg-utilities.js
GOldwasher/libraries/support/svg-pan-zoom/uniwheel.js
GOldwasher/libraries/support/svg-pan-zoom/utilities.js
GOldwasher/libraries/support/svg-pan-zoom/media/reset.ai
GOldwasher/libraries/support/svg-pan-zoom/media/reset.svg
GOldwasher/libraries/support/tab-content/tabbg.gif
GOldwasher/libraries/support/tab-content/tabcontent.css
GOldwasher/libraries/support/tab-content/tabcontent.js
bin/goldpanner