Metadata-Version: 1.0
Name: GOldwasher
Version: 0.2.8
Summary: Light wrapper for the R topGO package that produces
Home-page: http://github.com/hpsbastos/GOldwasher
Author: hpbastos
Author-email: hpb29@cam.ac.uk
License: GPLv3
Keywords: GOldwasher GO term enrichment visualization
Platform: UNKNOWN
